{"_type":"export","__export_format":4,"__export_date":"2019-12-31T14:43:51.737Z","__export_source":"insomnia.desktop.app:v7.0.6","resources":[{"_id":"req_a9e38de6f40b4f0eb03a20c8a840de93","authentication":{},"body":{"mimeType":"application/json","text":"{\n\t\"question\": \"Are you team monster or team mutant?\"\n}"},"created":1574028398768,"description":"","headers":[{"id":"pair_92672573f1af4b699910cc8eefe0ddb6","name":"Content-Type","value":"application/json"}],"isPrivate":false,"metaSortKey":-1574029725683,"method":"POST","modified":1576111740973,"name":"Create","parameters":[],"parentId":"fld_3422cf65fcd14a2f972fc3c52c01d61d","settingDisableRenderRequestBody":false,"settingEncodeUrl":true,"settingFollowRedirects":"global","settingRebuildPath":true,"settingSendCookies":true,"settingStoreCookies":true,"url":"{{ base_url  }}/students/10/help-orders","_type":"request"},{"_id":"fld_3422cf65fcd14a2f972fc3c52c01d61d","created":1574028371108,"description":"","environment":{},"environmentPropertyOrder":null,"metaSortKey":-1574028371108,"modified":1574028371108,"name":"HelpOrder-Question","parentId":"wrk_1f5e4468c509404ba98b9b5621e234c7","_type":"request_group"},{"_id":"wrk_1f5e4468c509404ba98b9b5621e234c7","created":1572789558582,"description":"","modified":1572789558582,"name":"GymPoint","parentId":null,"_type":"workspace"},{"_id":"req_76ca64d94e2a4b20afc9f1fa4ee8c034","authentication":{"token":"{{ admin_token  }}","type":"bearer"},"body":{},"created":1576108541210,"description":"","headers":[],"isPrivate":false,"metaSortKey":-1574029725658,"method":"GET","modified":1577387619477,"name":"ReadAllUnanswered","parameters":[{"description":"","disabled":true,"id":"pair_946e9895a20b48929589f667289b5c8e","name":"page","value":"1"}],"parentId":"fld_3422cf65fcd14a2f972fc3c52c01d61d","settingDisableRenderRequestBody":false,"settingEncodeUrl":true,"settingFollowRedirects":"global","settingRebuildPath":true,"settingSendCookies":true,"settingStoreCookies":true,"url":"{{ base_url  }}/help-orders","_type":"request"},{"_id":"req_a1c09919a3ab4e72a095341a6affe6f5","authentication":{},"body":{},"created":1574029725633,"description":"","headers":[],"isPrivate":false,"metaSortKey":-1574029725633,"method":"GET","modified":1577556991300,"name":"ReadStudentQuestion","parameters":[{"description":"","id":"pair_f8581b1cd4684d2f8ee34095dad384f1","name":"page","value":"2"}],"parentId":"fld_3422cf65fcd14a2f972fc3c52c01d61d","settingDisableRenderRequestBody":false,"settingEncodeUrl":true,"settingFollowRedirects":"global","settingRebuildPath":true,"settingSendCookies":true,"settingStoreCookies":true,"url":" {{ base_url  }}/students/8/help-orders","_type":"request"},{"_id":"req_d06660ab11fe426cb94388a44fe3acec","authentication":{},"body":{},"created":1577193073659,"description":"","headers":[],"isPrivate":false,"metaSortKey":-1577193073659,"method":"GET","modified":1577193237462,"name":"ReadOne","parameters":[],"parentId":"fld_2d700fda1b534a50b5de69d711972288","settingDisableRenderRequestBody":false,"settingEncodeUrl":true,"settingFollowRedirects":"global","settingRebuildPath":true,"settingSendCookies":true,"settingStoreCookies":true,"url":"{{ base_url  }}/help-orders/3","_type":"request"},{"_id":"fld_2d700fda1b534a50b5de69d711972288","created":1574028380389,"description":"","environment":{},"environmentPropertyOrder":null,"metaSortKey":-1574016310029,"modified":1574028384533,"name":"HelpOrder-Answer","parentId":"wrk_1f5e4468c509404ba98b9b5621e234c7","_type":"request_group"},{"_id":"req_1b8e6d365d6b49a09e8a2cb6689971b8","authentication":{"token":"{{ admin_token  }}","type":"bearer"},"body":{},"created":1574030164295,"description":"","headers":[],"isPrivate":false,"metaSortKey":-1574030466688,"method":"GET","modified":1577193037498,"name":"ReadAll","parameters":[],"parentId":"fld_2d700fda1b534a50b5de69d711972288","settingDisableRenderRequestBody":false,"settingEncodeUrl":true,"settingFollowRedirects":"global","settingRebuildPath":true,"settingSendCookies":true,"settingStoreCookies":true,"url":"{{ base_url  }}/help-orders","_type":"request"},{"_id":"req_88d20570c79c44809fce8d12237ca650","authentication":{"token":"{{ admin_token  }}","type":"bearer"},"body":{"mimeType":"application/json","text":"{\n\t\"answer\": \"If you had a mistake, do it again. And if it hurts, bear with it!\"\n}"},"created":1574030466638,"description":"","headers":[{"id":"pair_41316ebfe45d4146be95d0e789d675e6","name":"Content-Type","value":"application/json"}],"isPrivate":false,"metaSortKey":-1574030466638,"method":"POST","modified":1575422046629,"name":"Update","parameters":[],"parentId":"fld_2d700fda1b534a50b5de69d711972288","settingDisableRenderRequestBody":false,"settingEncodeUrl":true,"settingFollowRedirects":"global","settingRebuildPath":true,"settingSendCookies":true,"settingStoreCookies":true,"url":"{{ base_url  }}/help-orders/1/answer","_type":"request"},{"_id":"req_2e9196d5a9a946028f42c292efcca375","authentication":{},"body":{},"created":1574004259350,"description":"","headers":[],"isPrivate":false,"metaSortKey":-1574004259425,"method":"POST","modified":1577056216962,"name":"Create","parameters":[],"parentId":"fld_818cecf2894a4f56bd3cba10d7c6216c","settingDisableRenderRequestBody":false,"settingEncodeUrl":true,"settingFollowRedirects":"global","settingRebuildPath":true,"settingSendCookies":true,"settingStoreCookies":true,"url":"{{ base_url  }}/students/8/checkins","_type":"request"},{"_id":"fld_818cecf2894a4f56bd3cba10d7c6216c","created":1574004248950,"description":"","environment":{},"environmentPropertyOrder":null,"metaSortKey":-1574004248950,"modified":1574004248950,"name":"Checkins","parentId":"wrk_1f5e4468c509404ba98b9b5621e234c7","_type":"request_group"},{"_id":"req_66fe84d47d164d5799de8c519c6a3351","authentication":{},"body":{},"created":1574004328326,"description":"","headers":[],"isPrivate":false,"metaSortKey":-1574004259375,"method":"GET","modified":1577622355416,"name":"ReadAll","parameters":[{"description":"","id":"pair_61060d38a2ef4321a6b95b67df14ae63","name":"page","value":"1"}],"parentId":"fld_818cecf2894a4f56bd3cba10d7c6216c","settingDisableRenderRequestBody":false,"settingEncodeUrl":true,"settingFollowRedirects":"global","settingRebuildPath":true,"settingSendCookies":true,"settingStoreCookies":true,"url":"{{ base_url  }}/students/9/checkins","_type":"request"},{"_id":"req_309b8c45f73f4ec6bf95b5ea23f71d07","authentication":{"token":"{{ admin_token  }}","type":"bearer"},"body":{"mimeType":"application/json","text":"{\n\t\"student_id\": 11,\n\t\"plan_id\": 7,\n\t\"start_date\": \"2019-12-09\"\n}"},"created":1573237812533,"description":"","headers":[{"id":"pair_5cb7b81ab63647bb81b441d77c7c17a5","name":"Content-Type","value":"application/json"}],"isPrivate":false,"metaSortKey":-1573229542535.5,"method":"POST","modified":1575843538870,"name":"Create","parameters":[],"parentId":"fld_6521c30862df4e25b99b37bf36236a76","settingDisableRenderRequestBody":false,"settingEncodeUrl":true,"settingFollowRedirects":"global","settingRebuildPath":true,"settingSendCookies":true,"settingStoreCookies":true,"url":" {{ base_url  }}/enrollments","_type":"request"},{"_id":"fld_6521c30862df4e25b99b37bf36236a76","created":1573237799428,"description":"","environment":{},"environmentPropertyOrder":null,"metaSortKey":-1573237799428,"modified":1573237799428,"name":"Enrollment","parentId":"wrk_1f5e4468c509404ba98b9b5621e234c7","_type":"request_group"},{"_id":"req_a575e70d3ff14f7a8bdb8e7706fee272","authentication":{"token":"{{ admin_token  }}","type":"bearer"},"body":{},"created":1573240147358,"description":"","headers":[],"isPrivate":false,"metaSortKey":-1573229542485.5,"method":"GET","modified":1577406521027,"name":"ReadAll","parameters":[{"description":"","disabled":true,"id":"pair_fe034f0ecb66489e86ee8e6b6783c2f9","name":"page","value":"1"},{"description":"","disabled":true,"id":"pair_c0b121d39609438f977615029666c005","name":"perPage","value":"2"}],"parentId":"fld_6521c30862df4e25b99b37bf36236a76","settingDisableRenderRequestBody":false,"settingEncodeUrl":true,"settingFollowRedirects":"global","settingRebuildPath":true,"settingSendCookies":true,"settingStoreCookies":true,"url":"{{ base_url  }}/enrollments","_type":"request"},{"_id":"req_4e11c32a11524044b10d4fd4dbfecc0c","authentication":{"token":"{{ admin_token  }}","type":"bearer"},"body":{},"created":1576434648957,"description":"","headers":[],"isPrivate":false,"metaSortKey":-1573229542460.5,"method":"GET","modified":1577288260165,"name":"ReadOne","parameters":[],"parentId":"fld_6521c30862df4e25b99b37bf36236a76","settingDisableRenderRequestBody":false,"settingEncodeUrl":true,"settingFollowRedirects":"global","settingRebuildPath":true,"settingSendCookies":true,"settingStoreCookies":true,"url":"{{ base_url  }}/enrollments/6","_type":"request"},{"_id":"req_a6a10a50ae7c41d0b52669fec5e0745a","authentication":{"token":"{{ admin_token  }}","type":"bearer"},"body":{"mimeType":"application/json","text":"{\n\t\"plan_id\": 4,\n\t\"start_date\": \"2019-12-29\"\n}"},"created":1573907848734,"description":"","headers":[{"id":"pair_5e52bd0b135842758267a693c5bc765d","name":"Content-Type","value":"application/json"}],"isPrivate":false,"metaSortKey":-1573229542435.5,"method":"PUT","modified":1577287887559,"name":"Update","parameters":[],"parentId":"fld_6521c30862df4e25b99b37bf36236a76","settingDisableRenderRequestBody":false,"settingEncodeUrl":true,"settingFollowRedirects":"global","settingRebuildPath":true,"settingSendCookies":true,"settingStoreCookies":true,"url":"{{ base_url  }}/enrollments/37","_type":"request"},{"_id":"req_a013a2a6236744b9af6cab1bcb86094d","authentication":{"token":"{{ admin_token  }}","type":"bearer"},"body":{},"created":1573908591932,"description":"","headers":[],"isPrivate":false,"metaSortKey":-1573229542385.5,"method":"DELETE","modified":1575422198629,"name":"Delete","parameters":[],"parentId":"fld_6521c30862df4e25b99b37bf36236a76","settingDisableRenderRequestBody":false,"settingEncodeUrl":true,"settingFollowRedirects":"global","settingRebuildPath":true,"settingSendCookies":true,"settingStoreCookies":true,"url":"{{ base_url  }}/enrollments/1","_type":"request"},{"_id":"req_81639eaf54d84bfb836093d4597471da","authentication":{"disabled":false,"token":"{{ admin_token  }}","type":"bearer"},"body":{"mimeType":"application/json","text":"{\n\t\"title\": \"Diamond\",\n\t\"duration\": 6,\n\t\"price\": 89\n}"},"created":1573223579308,"description":"","headers":[{"id":"pair_a726eb32688e4c85987d38698a3e8c2b","name":"Content-Type","value":"application/json"}],"isPrivate":false,"metaSortKey":-1573223579308,"method":"POST","modified":1575421520253,"name":"Create","parameters":[],"parentId":"fld_839ada27b73e413b9d6c8dec20a74441","settingDisableRenderRequestBody":false,"settingEncodeUrl":true,"settingFollowRedirects":"global","settingRebuildPath":true,"settingSendCookies":true,"settingStoreCookies":true,"url":"{{ base_url  }}/plans","_type":"request"},{"_id":"fld_839ada27b73e413b9d6c8dec20a74441","created":1573221285643,"description":"","environment":{},"environmentPropertyOrder":null,"metaSortKey":-1573221285643,"modified":1573221285643,"name":"Plan","parentId":"wrk_1f5e4468c509404ba98b9b5621e234c7","_type":"request_group"},{"_id":"req_1235347e267f47779480c77073eb500f","authentication":{"token":"{{ admin_token  }}","type":"bearer"},"body":{},"created":1573221294426,"description":"","headers":[],"isPrivate":false,"metaSortKey":-1573221294426,"method":"GET","modified":1577562273879,"name":"ReadAll","parameters":[{"description":"","disabled":false,"id":"pair_a6f9d676a950456293cc78c4528c74e9","name":"page","value":"1"},{"description":"","disabled":false,"id":"pair_fef0dca76b5b494581b2d74b5be5aea9","name":"perPage","value":"15"}],"parentId":"fld_839ada27b73e413b9d6c8dec20a74441","settingDisableRenderRequestBody":false,"settingEncodeUrl":true,"settingFollowRedirects":"global","settingRebuildPath":true,"settingSendCookies":true,"settingStoreCookies":true,"url":"{{ base_url  }}/plans","_type":"request"},{"_id":"req_7f7cbc67acf74137b55101fabd46f093","authentication":{"token":"{{ admin_token  }}","type":"bearer"},"body":{"mimeType":"application/json","text":"{\n\t\"title\": \"Platinum\",\n\t\"duration\": 9,\n\t\"price\": 80\n}"},"created":1573227664776,"description":"","headers":[{"id":"pair_ed9ceec425b7420aabb142ecc37528e7","name":"Content-Type","value":"application/json"}],"isPrivate":false,"metaSortKey":-1573221294376,"method":"PUT","modified":1573227892832,"name":"Update","parameters":[],"parentId":"fld_839ada27b73e413b9d6c8dec20a74441","settingDisableRenderRequestBody":false,"settingEncodeUrl":true,"settingFollowRedirects":"global","settingRebuildPath":true,"settingSendCookies":true,"settingStoreCookies":true,"url":"{{ base_url  }}/plans/3","_type":"request"},{"_id":"req_856148da3e7b4388becf4b888a5bfdee","authentication":{"token":"{{ admin_token  }}","type":"bearer"},"body":{},"created":1573229206417,"description":"","headers":[],"isPrivate":false,"metaSortKey":-1573221294326,"method":"DELETE","modified":1573229227890,"name":"Delete","parameters":[],"parentId":"fld_839ada27b73e413b9d6c8dec20a74441","settingDisableRenderRequestBody":false,"settingEncodeUrl":true,"settingFollowRedirects":"global","settingRebuildPath":true,"settingSendCookies":true,"settingStoreCookies":true,"url":"{{ base_url  }}/plans/3","_type":"request"},{"_id":"req_c83b9cf6f4764f498e0195238b403e6e","authentication":{"token":"{{ admin_token  }}","type":"bearer"},"body":{"mimeType":"application/json","text":"{\n\t\"name\": \"Astolfo\",\n\t\"email\": \"astolfo@gmail.com\",\n\t\"age\": 63,\n\t\"weight\": 43.8,\n\t\"height\": 1.62\n}"},"created":1573076556532,"description":"","headers":[{"id":"pair_4f90e71b4dbd44c4b1fffbc7b8561aaa","name":"Content-Type","value":"application/json"}],"isPrivate":false,"metaSortKey":-1573188151544.5,"method":"POST","modified":1575422934702,"name":"Create","parameters":[],"parentId":"fld_26fe24e029ec4a398eae124e19ad4b25","settingDisableRenderRequestBody":false,"settingEncodeUrl":true,"settingFollowRedirects":"global","settingRebuildPath":true,"settingSendCookies":true,"settingStoreCookies":true,"url":"{{ base_url  }}/students","_type":"request"},{"_id":"fld_26fe24e029ec4a398eae124e19ad4b25","created":1573076545096,"description":"","environment":{},"environmentPropertyOrder":null,"metaSortKey":-1573076545096,"modified":1573076545096,"name":"Students","parentId":"wrk_1f5e4468c509404ba98b9b5621e234c7","_type":"request_group"},{"_id":"req_6347cf83f9f24fedae067aa7e9285025","authentication":{"token":"{{ admin_token  }}","type":"bearer"},"body":{},"created":1573225349882,"description":"","headers":[],"isPrivate":false,"metaSortKey":-1573169552375.75,"method":"GET","modified":1577393685379,"name":"ReadAll","parameters":[{"disabled":true,"id":"pair_5eb1a05336dd4d76bdd903cd6068c530","name":"name","value":"a"},{"description":"","disabled":false,"id":"pair_0c5262c4b32f4c9eac037e0d32ff05f0","name":"page","value":"1"}],"parentId":"fld_26fe24e029ec4a398eae124e19ad4b25","settingDisableRenderRequestBody":false,"settingEncodeUrl":true,"settingFollowRedirects":"global","settingRebuildPath":true,"settingSendCookies":true,"settingStoreCookies":true,"url":"{{ base_url  }}/students","_type":"request"},{"_id":"req_cef1573baa5f4d8ea083b67ee3e66bfb","authentication":{},"body":{},"created":1576965259000,"description":"","headers":[],"isPrivate":false,"metaSortKey":-1573160252791.375,"method":"GET","modified":1577208508900,"name":"ReadOne","parameters":[],"parentId":"fld_26fe24e029ec4a398eae124e19ad4b25","settingDisableRenderRequestBody":false,"settingEncodeUrl":true,"settingFollowRedirects":"global","settingRebuildPath":true,"settingSendCookies":true,"settingStoreCookies":true,"url":"{{ base_url  }}/students/8","_type":"request"},{"_id":"req_f462e2b396214a71b4dbefba3d0cce66","authentication":{"token":"{{ admin_token  }}","type":"bearer"},"body":{"mimeType":"application/json","text":"{\n\t\"name\": \"Roberval\",\n\t\"email\": \"roberval@gmail.com\",\n\t\"age\": 62,\n\t\"weight\": 81.9,\n\t\"height\": 1.73\n}"},"created":1573076969097,"description":"","headers":[{"id":"pair_4f90e71b4dbd44c4b1fffbc7b8561aaa","name":"Content-Type","value":"application/json"}],"isPrivate":false,"metaSortKey":-1573150953207,"method":"PUT","modified":1573228141060,"name":"Update","parameters":[],"parentId":"fld_26fe24e029ec4a398eae124e19ad4b25","settingDisableRenderRequestBody":false,"settingEncodeUrl":true,"settingFollowRedirects":"global","settingRebuildPath":true,"settingSendCookies":true,"settingStoreCookies":true,"url":"{{ base_url  }}/students/4","_type":"request"},{"_id":"req_cb688e7d47194410afc3086605ef5387","authentication":{"token":"{{ admin_token  }}","type":"bearer"},"body":{},"created":1573230225308,"description":"","headers":[],"isPrivate":false,"metaSortKey":-1573150953157,"method":"DELETE","modified":1575421870542,"name":"Delete","parameters":[],"parentId":"fld_26fe24e029ec4a398eae124e19ad4b25","settingDisableRenderRequestBody":false,"settingEncodeUrl":true,"settingFollowRedirects":"global","settingRebuildPath":true,"settingSendCookies":true,"settingStoreCookies":true,"url":"{{ base_url  }}/students/2","_type":"request"},{"_id":"req_9593fbfe98da46debc19a4048ba22411","authentication":{},"body":{"mimeType":"application/json","text":"{\n\t\"email\": \"admin@gympoint.com\",\n\t\"password\": \"123456\"\n}"},"created":1572820561106,"description":"","headers":[{"id":"pair_46326dcfc4584af2821bff0dcd0099ae","name":"Content-Type","value":"application/json"}],"isPrivate":false,"metaSortKey":-1572820561106,"method":"POST","modified":1573081682797,"name":"Create","parameters":[],"parentId":"fld_b276e8c029d54686a3452d6912aca3cc","settingDisableRenderRequestBody":false,"settingEncodeUrl":true,"settingFollowRedirects":"global","settingRebuildPath":true,"settingSendCookies":true,"settingStoreCookies":true,"url":"{{ base_url  }}/sessions","_type":"request"},{"_id":"fld_b276e8c029d54686a3452d6912aca3cc","created":1572820551038,"description":"","environment":{},"environmentPropertyOrder":null,"metaSortKey":-1572820551038,"modified":1572820551038,"name":"Sessions","parentId":"wrk_1f5e4468c509404ba98b9b5621e234c7","_type":"request_group"},{"_id":"req_38252683338644bcbffe59125c6bd276","authentication":{"type":"bearer"},"body":{"mimeType":"application/json","text":"{\n\t\"name\": \"Admin3\",\n\t\"email\": \"admin3@gympoint.com\",\n\t\"password\": \"123456\"\n}"},"created":1572789575031,"description":"","headers":[{"id":"pair_77c8a4d0d9f24805830e2dbe8c907de1","name":"Content-Type","value":"application/json"}],"isPrivate":false,"metaSortKey":-1572821756409,"method":"POST","modified":1572821885015,"name":"Create","parameters":[],"parentId":"fld_473a42f1f280443690d4a870c9cb59ed","settingDisableRenderRequestBody":false,"settingEncodeUrl":true,"settingFollowRedirects":"global","settingRebuildPath":true,"settingSendCookies":true,"settingStoreCookies":true,"url":"{{ base_url  }}/users","_type":"request"},{"_id":"fld_473a42f1f280443690d4a870c9cb59ed","created":1572789564579,"description":"","environment":{},"environmentPropertyOrder":null,"metaSortKey":-1572789564579,"modified":1572789564579,"name":"Users","parentId":"wrk_1f5e4468c509404ba98b9b5621e234c7","_type":"request_group"},{"_id":"req_79f28ef7b8c446fe820993bb965b18ac","authentication":{"token":"{{ admin_token  }}","type":"bearer"},"body":{"mimeType":"application/json","text":"{\n\t\"name\": \"Admin3\",\n\t\"email\": \"admin_oi@gympoint.com\",\n\t\"oldPassword\": \"123456\",\n\t\"password\": \"1234567\"\n}"},"created":1572821756359,"description":"","headers":[{"id":"pair_1502d4bcba7b42fe9454d328d467f075","name":"Content-Type","value":"application/json"}],"isPrivate":false,"metaSortKey":-1572821756359,"method":"PUT","modified":1573076105933,"name":"Update","parameters":[],"parentId":"fld_473a42f1f280443690d4a870c9cb59ed","settingDisableRenderRequestBody":false,"settingEncodeUrl":true,"settingFollowRedirects":"global","settingRebuildPath":true,"settingSendCookies":true,"settingStoreCookies":true,"url":"{{ base_url  }}/users","_type":"request"},{"_id":"env_0b3ba0ad585b60ec3942244f44d6f4cacf6be828","color":null,"created":1572789558765,"data":{"admin_token":"eyJhbGciOiJIUzI1NiIsInR5cCI6IkpXVCJ9.eyJpZCI6MSwiaWF0IjoxNTc3MTkzMDQ0LCJleHAiOjE1Nzc3OTc4NDR9.-uiNJW3k7EtO9ssqB9CpPUKbFohacwzzA-XcIcOBNmQ","base_url":"http://localhost:3333"},"dataPropertyOrder":{"&":["base_url","admin_token"]},"isPrivate":false,"metaSortKey":1572789558765,"modified":1577193056034,"name":"Base Environment","parentId":"wrk_1f5e4468c509404ba98b9b5621e234c7","_type":"environment"},{"_id":"jar_0b3ba0ad585b60ec3942244f44d6f4cacf6be828","cookies":[],"created":1572789558767,"modified":1572789558767,"name":"Default Jar","parentId":"wrk_1f5e4468c509404ba98b9b5621e234c7","_type":"cookie_jar"}]}